pipelitools/__init__.py
pipelitools/utils.py
pipelitools/models/__init__.py
pipelitools/models/clustering.py
pipelitools/models/cnn.py
pipelitools/models/metrics.py
pipelitools/models/models.py
pipelitools/preprocessing/__init__.py
pipelitools/preprocessing/eda.py
pipelitools/preprocessing/features.py
pipelitools/preprocessing/outliers.py
pipelitools-1.1.4.dist-info/LICENSE.txt
pipelitools-1.1.4.dist-info/METADATA
pipelitools-1.1.4.dist-info/WHEEL
pipelitools-1.1.4.dist-info/top_level.txt
pipelitools-1.1.4.dist-info/RECORD
