Metadata-Version: 2.1
Name: pipelitools
Version: 1.1.4
Summary: Tools for data analysis
Home-page: https://github.com/nastiag67/pipelitools
Author: Anastasia Glushkova
Author-email: anastasia.glushkova0@yandex.ru
License: MIT license
Keywords: pipelitools
Platform: UNKNOWN
Classifier: Development Status :: 2 - Pre-Alpha
Classifier: Intended Audience :: Developers
Classifier: License :: OSI Approved :: MIT License
Classifier: Natural Language :: English
Classifier: Programming Language :: Python :: 3
Classifier: Programming Language :: Python :: 3.6
Classifier: Programming Language :: Python :: 3.7
Classifier: Programming Language :: Python :: 3.8
Classifier: Operating System :: OS Independent
Requires-Python: >=3.6
Requires-Dist: pandas
Requires-Dist: numpy
Requires-Dist: scipy
Requires-Dist: seaborn
Requires-Dist: matplotlib
Requires-Dist: pandas-profiling
Requires-Dist: sklearn
Requires-Dist: datetime
